arxiv_update_cli.py
arxiv_update_cli-1.2.1.dist-info/licenses/LICENSE
arxiv_update_cli-1.2.1.dist-info/METADATA
arxiv_update_cli-1.2.1.dist-info/WHEEL
arxiv_update_cli-1.2.1.dist-info/entry_points.txt
arxiv_update_cli-1.2.1.dist-info/top_level.txt
arxiv_update_cli-1.2.1.dist-info/RECORD
