Metadata-Version: 2.4
Name: arxiv_update_cli
Version: 1.2.1
Summary: Fetch new articles on arXiv by keywords
Home-page: https://gitlab.com/j_4321/arxivscript
Author: Juliette Monsel
Author-email: j_4321@protonmail.com
License: MIT
Classifier: Development Status :: 5 - Production/Stable
Classifier: Intended Audience :: Science/Research
Classifier: Environment :: Console
Classifier: Topic :: Scientific/Engineering
Classifier: Operating System :: OS Independent
Classifier: License :: OSI Approved :: MIT License
Classifier: Programming Language :: Python :: 3
Classifier: Natural Language :: English
License-File: LICENSE
Requires-Dist: feedparser
Provides-Extra: store-password-in-system-keyring
Requires-Dist: keyring; extra == "store-password-in-system-keyring"
Provides-Extra: progressbar-for-file-downloads
Requires-Dist: tqdm; extra == "progressbar-for-file-downloads"
Provides-Extra: import-articles-in-zotero-library
Requires-Dist: pyzotero; extra == "import-articles-in-zotero-library"
Provides-Extra: tab-autocompletion-in-interactive-mode
Requires-Dist: pyreadline3; sys_platform == "win32" and extra == "tab-autocompletion-in-interactive-mode"
Dynamic: author
Dynamic: author-email
Dynamic: classifier
Dynamic: description
Dynamic: description-content-type
Dynamic: home-page
Dynamic: license
Dynamic: license-file
Dynamic: provides-extra
Dynamic: requires-dist
Dynamic: summary
